voltaire_bundler/.dockerignore
voltaire_bundler/__init__.py
voltaire_bundler/__main__.py
voltaire_bundler/boot.py
voltaire_bundler/bundler/__init__.py
voltaire_bundler/bundler/bundle/bundle_manager.py
voltaire_bundler/bundler/entrypoint.py
voltaire_bundler/bundler/entrypoints/entrypoint.py
voltaire_bundler/bundler/entrypoints/mempool.py
voltaire_bundler/bundler/entrypoints/useroperations_with_entrypoint.py
voltaire_bundler/bundler/exceptions.py
voltaire_bundler/bundler/execution_endpoint.py
voltaire_bundler/bundler/gas_manager.py
voltaire_bundler/bundler/mempool/mempool_info.py
voltaire_bundler/bundler/mempool/mempool_manager.py
voltaire_bundler/bundler/mempool/mempool_member.py
voltaire_bundler/bundler/mempool/sender_mempool.py
voltaire_bundler/bundler/reputation_manager.py
voltaire_bundler/bundler/validation_manager.py
voltaire_bundler/event_bus_manager/__init__.py
voltaire_bundler/event_bus_manager/endpoint.py
voltaire_bundler/main.py
voltaire_bundler/metrics/__init__.py
voltaire_bundler/metrics/metrics.py
voltaire_bundler/rpc/__init__.py
voltaire_bundler/rpc/rpc_http_server.py
voltaire_bundler/typing.py
voltaire_bundler/user_operation/models.py
voltaire_bundler/user_operation/user_operation.py
voltaire_bundler/user_operation/user_operation_handler.py
voltaire_bundler/utils/BundlerCollectorTracer.js
voltaire_bundler/utils/BundlerHelper.json
voltaire_bundler/utils/BundlerHelper.sol
voltaire_bundler/utils/SignalHaltError.py
voltaire_bundler/utils/decode.py
voltaire_bundler/utils/encode.py
voltaire_bundler/utils/eth_client_utils.py
voltaire_bundler/utils/import_key.py
voltaire_bundler-0.1.0a24.dist-info/LICENSE
voltaire_bundler-0.1.0a24.dist-info/METADATA
voltaire_bundler-0.1.0a24.dist-info/WHEEL
voltaire_bundler-0.1.0a24.dist-info/entry_points.txt
voltaire_bundler-0.1.0a24.dist-info/RECORD
