Metadata-Version: 2.1
Name: voltaire_bundler
Version: 0.1.0a24
Summary: EIP-4337 python Bundler
Home-page: https://github.com/candidelabs/voltaire
License: LGPL
Keywords: 4337,account_abstraction,ethereum,bundler
Author: Candide Wallet Team
Requires-Python: >=3.11,<4.0
Classifier: Development Status :: 3 - Alpha
Classifier: Environment :: Console
Classifier: License :: OSI Approved :: GNU Library or Lesser General Public License (LGPL)
Classifier: License :: Other/Proprietary License
Classifier: Operating System :: POSIX :: Linux
Classifier: Programming Language :: Python :: 3
Classifier: Programming Language :: Python :: 3.11
Classifier: Programming Language :: Python :: 3.12
Requires-Dist: aiohttp (>=3.9.1,<4.0.0)
Requires-Dist: aiohttp-cors (>=0.7.0,<0.8.0)
Requires-Dist: eth-abi (>=4.1.0,<5.0.0)
Requires-Dist: eth-account (>=0.8.0,<0.9.0)
Requires-Dist: jsonrpcserver (>=5.0.9,<6.0.0)
Requires-Dist: prometheus-client (>=0.17.1,<0.18.0)
Requires-Dist: uvloop (>=0.19.0,<0.20.0)
Project-URL: Repository, https://github.com/candidelabs/voltaire
